json_management/__init__.py
json_management/json_management.py
json_management-0.0.3.dist-info/LICENSE
json_management-0.0.3.dist-info/METADATA
json_management-0.0.3.dist-info/WHEEL
json_management-0.0.3.dist-info/top_level.txt
json_management-0.0.3.dist-info/RECORD
