Metadata-Version: 2.1
Name: json_management
Version: 0.0.3
Author: unixtux
License: GNU GENERAL PUBLIC LICENSE
Project-URL: Repository, https://github.com/unixtux/json_management
Requires-Python: >=3.8
License-File: LICENSE
Requires-Dist: aiotgm
